setup.py
naclautomake/__init__.py
naclautomake/common.py
naclautomake/define.py
naclautomake/main.py
naclautomake/makefile.py
naclautomake/project.py
naclautomake/setting.py
naclautomake/solution.py
naclautomake.egg-info/PKG-INFO
naclautomake.egg-info/SOURCES.txt
naclautomake.egg-info/dependency_links.txt
naclautomake.egg-info/top_level.txt