Metadata-Version: 1.1
Name: naclautomake
Version: 0.0.1
Summary: Automake of Native Client from Google
Home-page: http://alexchi.me/
Author: Alex Chi
Author-email: alex@alexchi.me
License: Creative Commons Attribution 3.0 Unported License
Platform: UNKNOWN
Classifier: Programming Language :: Python
Classifier: Programming Language :: Python :: 2.7
Classifier: Development Status :: 1 - Planning
Classifier: License :: OSI Approved
Classifier: Operating System :: OS Independent
Classifier: Topic :: Software Development
Classifier: Topic :: Utilities
